aiolifx_effects/__init__.py
aiolifx_effects/aiolifx_effects.py
aiolifx_effects-0.3.2.dist-info/LICENSE.txt
aiolifx_effects-0.3.2.dist-info/METADATA
aiolifx_effects-0.3.2.dist-info/WHEEL
aiolifx_effects-0.3.2.dist-info/top_level.txt
aiolifx_effects-0.3.2.dist-info/RECORD
